{
  "type": "input",
  "version": "0.0.0",
  "large_object": {
    "length": 587,
    "width": 233,
    "height": 220
  },
  "small_items": [
    {
      "length": 78,
      "width": 72,
      "height": 58,
      "quantity": 10
    },
    {
      "length": 107,
      "width": 57,
      "height": 57,
      "quantity": 11
    },
    {
      "length": 72,
      "width": 64,
      "height": 37,
      "quantity": 15
    },
    {
      "length": 93,
      "width": 66,
      "height": 26,
      "quantity": 13
    },
    {
      "length": 116,
      "width": 67,
      "height": 35,
      "quantity": 12
    },
    {
      "length": 101,
      "width": 56,
      "height": 39,
      "quantity": 11
    },
    {
      "length": 108,
      "width": 100,
      "height": 39,
      "quantity": 9
    },
    {
      "length": 64,
      "width": 55,
      "height": 33,
      "quantity": 9
    },
    {
      "length": 73,
      "width": 65,
      "height": 53,
      "quantity": 7
    },
    {
      "length": 106,
      "width": 41,
      "height": 35,
      "quantity": 10
    },
    {
      "length": 82,
      "width": 78,
      "height": 28,
      "quantity": 11
    },
    {
      "length": 79,
      "width": 59,
      "height": 58,
      "quantity": 9
    }
  ]
}