{
  "type": "input",
  "version": "0.3.0",
  "large_object": {
    "measurement": {
      "x": 587,
      "y": 233,
      "z": 220
    }
  },
  "small_items": [
    {
      "measurement": {
        "x": 65,
        "y": 51,
        "z": 50
      },
      "quantity": 51,
      "constraint": {
        "orientation": {
          "xyz": true,
          "yxz": true,
          "zyx": true,
          "xzy": true,
          "zxy": true,
          "yzx": true
        }
      }
    },
    {
      "measurement": {
        "x": 113,
        "y": 78,
        "z": 28
      },
      "quantity": 56,
      "constraint": {
        "orientation": {
          "xyz": true,
          "yxz": true,
          "zyx": false,
          "xzy": false,
          "zxy": false,
          "yzx": false
        }
      }
    },
    {
      "measurement": {
        "x": 120,
        "y": 35,
        "z": 32
      },
      "quantity": 57,
      "constraint": {
        "orientation": {
          "xyz": true,
          "yxz": true,
          "zyx": false,
          "xzy": true,
          "zxy": true,
          "yzx": false
        }
      }
    }
  ]
}