{
  "type": "input",
  "version": "0.3.0",
  "large_object": {
    "measurement": {
      "x": 587,
      "y": 233,
      "z": 220
    }
  },
  "small_items": [
    {
      "measurement": {
        "x": 119,
        "y": 34,
        "z": 28
      },
      "quantity": 39,
      "constraint": {
        "orientation": {
          "xyz": true,
          "yxz": true,
          "zyx": false,
          "xzy": true,
          "zxy": true,
          "yzx": false
        }
      }
    },
    {
      "measurement": {
        "x": 84,
        "y": 69,
        "z": 48
      },
      "quantity": 32,
      "constraint": {
        "orientation": {
          "xyz": true,
          "yxz": true,
          "zyx": true,
          "xzy": true,
          "zxy": true,
          "yzx": true
        }
      }
    },
    {
      "measurement": {
        "x": 97,
        "y": 82,
        "z": 78
      },
      "quantity": 27,
      "constraint": {
        "orientation": {
          "xyz": true,
          "yxz": true,
          "zyx": true,
          "xzy": true,
          "zxy": true,
          "yzx": true
        }
      }
    }
  ]
}